agentwatch/__init__.py
agentwatch/cli.py
agentwatch/discovery.py
agentwatch/detectors/__init__.py
agentwatch/detectors/base.py
agentwatch/detectors/registry.py
agentwatch/detectors/health/__init__.py
agentwatch/detectors/health/_window.py
agentwatch/detectors/health/behavioral.py
agentwatch/detectors/health/constraints.py
agentwatch/detectors/health/context.py
agentwatch/detectors/health/errors.py
agentwatch/detectors/health/loops.py
agentwatch/detectors/health/progress.py
agentwatch/detectors/health/repetition.py
agentwatch/detectors/health/stuck.py
agentwatch/detectors/health/tool_thrash.py
agentwatch/detectors/security/__init__.py
agentwatch/detectors/security/credentials.py
agentwatch/detectors/security/injection.py
agentwatch/detectors/security/network.py
agentwatch/detectors/security/privilege.py
agentwatch/detectors/security/supply_chain.py
agentwatch/health/__init__.py
agentwatch/health/rot.py
agentwatch/health/score.py
agentwatch/parser/__init__.py
agentwatch/parser/logs.py
agentwatch/parser/models.py
agentwatch/parser/watcher.py
agentwatch/ui/__init__.py
agentwatch/ui/app.py
agentwatch/ui/multi_app.py
agentwatch/ui/rot_widget.py
agentwatch_monitor-0.1.dist-info/METADATA
agentwatch_monitor-0.1.dist-info/WHEEL
agentwatch_monitor-0.1.dist-info/entry_points.txt
agentwatch_monitor-0.1.dist-info/licenses/LICENSE
agentwatch_monitor-0.1.dist-info/RECORD
