Metadata-Version: 2.4
Name: agentwatch-monitor
Version: 0.1
Summary: Real-time health and security monitoring for AI coding agents
Author: LoomLabs
License: MIT
License-File: LICENSE
Keywords: agent,ai,claude,llm,moltbot,monitoring,security
Classifier: Development Status :: 3 - Alpha
Classifier: Environment :: Console
Classifier: Intended Audience :: Developers
Classifier: Intended Audience :: System Administrators
Classifier: License :: OSI Approved :: MIT License
Classifier: Programming Language :: Python :: 3.11
Classifier: Programming Language :: Python :: 3.12
Classifier: Topic :: Security
Classifier: Topic :: Software Development :: Quality Assurance
Requires-Python: >=3.11
Requires-Dist: click>=8.0.0
Requires-Dist: pydantic>=2.0.0
Requires-Dist: textual>=0.50.0
Requires-Dist: watchfiles>=0.21.0
Provides-Extra: dev
Requires-Dist: pytest-asyncio>=0.23.0; extra == 'dev'
Requires-Dist: pytest>=8.0.0; extra == 'dev'
Requires-Dist: ruff>=0.3.0; extra == 'dev'
Provides-Extra: llm
Requires-Dist: anthropic>=0.18.0; extra == 'llm'
Requires-Dist: ollama>=0.1.0; extra == 'llm'
Provides-Extra: siem
Requires-Dist: python-json-logger>=2.0.0; extra == 'siem'
